.gitignore
MANIFEST.in
README.txt
setup.cfg
setup.py
adi/__init__.py
adi.dropdownmenu.egg-info/PKG-INFO
adi.dropdownmenu.egg-info/SOURCES.txt
adi.dropdownmenu.egg-info/dependency_links.txt
adi.dropdownmenu.egg-info/entry_points.txt
adi.dropdownmenu.egg-info/namespace_packages.txt
adi.dropdownmenu.egg-info/not-zip-safe
adi.dropdownmenu.egg-info/paster_plugins.txt
adi.dropdownmenu.egg-info/requires.txt
adi.dropdownmenu.egg-info/top_level.txt
adi/dropdownmenu/__init__.py
adi/dropdownmenu/adi_dropdown.css
adi/dropdownmenu/configure.zcml
adi/dropdownmenu/interfaces.py
adi/dropdownmenu/tests.py
adi/dropdownmenu/browser/__init__.py
adi/dropdownmenu/browser/configure.zcml
adi/dropdownmenu/browser/resources/main.js
adi/dropdownmenu/browser/resources/mobile.css
adi/dropdownmenu/browser/resources/mobile.scss
adi/dropdownmenu/profiles/default/browserlayer.xml
adi/dropdownmenu/profiles/default/cssregistry.xml
adi/dropdownmenu/profiles/default/jsregistry.xml
adi/dropdownmenu/profiles/default/metadata.xml
adi/dropdownmenu/profiles/default/portlets.xml
adi/dropdownmenu/profiles/default/viewlets.xml
docs/HISTORY.txt
docs/LICENSE.GPL
docs/LICENSE.txt