Metadata-Version: 1.1
Name: adi.dropdownmenu
Version: 0.7
Summary: A dropdownmenu that is configurable for site administrators and mirrows your folderstructures.
Home-page: http://svn.plone.org/svn/collective/adi.dropdownmenu
Author: Ida Ebkes
Author-email: contakt@ida-ebkes.eu
License: GPL
Platform: UNKNOWN
Classifier: Framework :: Plone
Classifier: Programming Language :: Python
